s3imageservice/__init__.py
s3imageservice/admin.py
s3imageservice/apps.py
s3imageservice/celery.py
s3imageservice/conf.py
s3imageservice/urls.py
s3imageservice/cms/__init__.py
s3imageservice/cms/urls.py
s3imageservice/cms/serializers/__init__.py
s3imageservice/cms/serializers/upload.py
s3imageservice/cms/views/__init__.py
s3imageservice/cms/views/base.py
s3imageservice/cms/views/detail.py
s3imageservice/cms/views/list.py
s3imageservice/cms/views/upload.py
s3imageservice/cms/viewsets/__init__.py
s3imageservice/cms/viewsets/upload.py
s3imageservice/migrations/0001_initial.py
s3imageservice/migrations/0002_upload_slug.py
s3imageservice/migrations/__init__.py
s3imageservice/models/__init__.py
s3imageservice/models/upload.py
s3imageservice/static/s3imageservice/css/main.detail.css
s3imageservice/static/s3imageservice/css/main.list.css
s3imageservice/static/s3imageservice/css/main.upload.css
s3imageservice/static/s3imageservice/js/main.detail.js
s3imageservice/static/s3imageservice/js/main.list.js
s3imageservice/static/s3imageservice/js/main.upload.js
s3imageservice/tasks/__init__.py
s3imageservice/tasks/aws.py
s3imageservice/tasks/process_images.py
s3imageservice/templates/base.html
s3imageservice/templates/detail.html
s3imageservice/templates/list.html
s3imageservice/templates/upload.html
s3imageservice/templates/s3imageservice/base.html
s3imageservice/templates/s3imageservice/detail.html
s3imageservice/templates/s3imageservice/list.html
s3imageservice/templates/s3imageservice/upload.html
s3imageservice/utils/__init__.py
s3imageservice/utils/auth.py
s3imageservice/utils/aws.py
s3imageservice/utils/importers.py
s3imageservice/views/__init__.py
s3imageservice/views/image_service.py
django_s3_image_service-1.0.6.dist-info/LICENSE
django_s3_image_service-1.0.6.dist-info/METADATA
django_s3_image_service-1.0.6.dist-info/WHEEL
django_s3_image_service-1.0.6.dist-info/top_level.txt
django_s3_image_service-1.0.6.dist-info/RECORD
